{"US": {"totalCases": 550145, "newCases": 17266, "active": 497376, "casesPerCapita": 1662}, "ES": {"totalCases": 166019, "newCases": 2992, "active": 86656, "casesPerCapita": 3551}, "IT": {"totalCases": 156363, "newCases": 4092, "active": 102253, "casesPerCapita": 2586}, "FR": {"totalCases": 132591, "newCases": 2937, "active": 91012, "casesPerCapita": 2031}, "DE": {"totalCases": 126656, "newCases": 1204, "active": 63448, "casesPerCapita": 1512}, "GB": {"totalCases": 84279, "newCases": 5288, "active": 73323, "casesPerCapita": 1241}, "IR": {"totalCases": 71686, "newCases": 1657, "active": 23318, "casesPerCapita": 853}, "TR": {"totalCases": 56956, "newCases": 4789, "active": 52312, "casesPerCapita": 675}, "BE": {"totalCases": 29647, "newCases": 1629, "active": 19584, "casesPerCapita": 2558}, "NL": {"totalCases": 25587, "newCases": 1174, "active": 22600, "casesPerCapita": 1493}, "CH": {"totalCases": 25407, "newCases": 300, "active": 11601, "casesPerCapita": 2936}, "CA": {"totalCases": 23738, "newCases": 420, "active": 16403, "casesPerCapita": 629}, "BR": {"totalCases": 21065, "newCases": 103, "active": 19748, "casesPerCapita": 99}, "PT": {"totalCases": 16585, "newCases": 598, "active": 15804, "casesPerCapita": 1627}, "RU": {"totalCases": 15770, "newCases": 2186, "active": 14349, "casesPerCapita": 108}, "AT": {"totalCases": 13945, "newCases": 139, "active": 6608, "casesPerCapita": 1548}, "IL": {"totalCases": 10878, "newCases": 135, "active": 9387, "casesPerCapita": 1257}, "KR": {"totalCases": 10512, "newCases": 32, "active": 2930, "casesPerCapita": 205}, "SE": {"totalCases": 10483, "newCases": 332, "active": 9203, "casesPerCapita": 1038}, "IE": {"totalCases": 9655, "newCases": 727, "active": 9296, "casesPerCapita": 1955}, "IN": {"totalCases": 9166, "newCases": 720, "active": 7780, "casesPerCapita": 7}, "EC": {"totalCases": 7466, "newCases": 209, "active": 6632, "casesPerCapita": 423}, "CL": {"totalCases": 7213, "newCases": 286, "active": 5074, "casesPerCapita": 377}, "PE": {"totalCases": 6848, "newCases": 0, "active": 4928, "casesPerCapita": 208}, "JP": {"totalCases": 6748, "newCases": 0, "active": 5878, "casesPerCapita": 53}, "PL": {"totalCases": 6674, "newCases": 318, "active": 6003, "casesPerCapita": 176}, "NO": {"totalCases": 6485, "newCases": 76, "active": 6327, "casesPerCapita": 1196}, "AU": {"totalCases": 6313, "newCases": 10, "active": 2916, "casesPerCapita": 248}, "RO": {"totalCases": 6300, "newCases": 310, "active": 5132, "casesPerCapita": 327}, "DK": {"totalCases": 6174, "newCases": 178, "active": 3778, "casesPerCapita": 1066}, "CZ": {"totalCases": 5952, "newCases": 50, "active": 5350, "casesPerCapita": 556}, "PK": {"totalCases": 5230, "newCases": 219, "active": 4111, "casesPerCapita": 24}, "MY": {"totalCases": 4683, "newCases": 153, "active": 2499, "casesPerCapita": 145}, "PH": {"totalCases": 4648, "newCases": 220, "active": 4154, "casesPerCapita": 42}, "SA": {"totalCases": 4462, "newCases": 429, "active": 3642, "casesPerCapita": 128}, "ID": {"totalCases": 4241, "newCases": 399, "active": 3509, "casesPerCapita": 16}, "MX": {"totalCases": 4219, "newCases": 375, "active": 2174, "casesPerCapita": 33}, "RS": {"totalCases": 3630, "newCases": 250, "active": 3150, "casesPerCapita": 415}, "LU": {"totalCases": 3281, "newCases": 11, "active": 2715, "casesPerCapita": 5241}, "PA": {"totalCases": 3234, "newCases": 0, "active": 3132, "casesPerCapita": 750}, "QA": {"totalCases": 2979, "newCases": 251, "active": 2697, "casesPerCapita": 1034}, "FI": {"totalCases": 2974, "newCases": 69, "active": 2618, "casesPerCapita": 537}, "DO": {"totalCases": 2967, "newCases": 208, "active": 2663, "casesPerCapita": 274}, "UA": {"totalCases": 2777, "newCases": 266, "active": 2605, "casesPerCapita": 63}, "CO": {"totalCases": 2709, "newCases": 0, "active": 2395, "casesPerCapita": 53}, "BY": {"totalCases": 2578, "newCases": 352, "active": 2349, "casesPerCapita": 273}, "TH": {"totalCases": 2551, "newCases": 33, "active": 1295, "casesPerCapita": 37}, "SG": {"totalCases": 2532, "newCases": 233, "active": 1964, "casesPerCapita": 433}, "ZA": {"totalCases": 2173, "newCases": 145, "active": 1738, "casesPerCapita": 37}, "AR": {"totalCases": 2142, "newCases": 0, "active": 1584, "casesPerCapita": 47}, "GR": {"totalCases": 2114, "newCases": 33, "active": 1747, "casesPerCapita": 203}, "EG": {"totalCases": 1939, "newCases": 0, "active": 1367, "casesPerCapita": 19}, "DZ": {"totalCases": 1914, "newCases": 89, "active": 1030, "casesPerCapita": 44}, "IS": {"totalCases": 1701, "newCases": 12, "active": 804, "casesPerCapita": 4985}, "MD": {"totalCases": 1662, "newCases": 102, "active": 1537, "casesPerCapita": 412}, "MA": {"totalCases": 1661, "newCases": 116, "active": 1366, "casesPerCapita": 45}, "HR": {"totalCases": 1600, "newCases": 66, "active": 1204, "casesPerCapita": 390}, "HU": {"totalCases": 1410, "newCases": 100, "active": 1193, "casesPerCapita": 146}, "IQ": {"totalCases": 1352, "newCases": 34, "active": 636, "casesPerCapita": 34}, "NZ": {"totalCases": 1330, "newCases": 18, "active": 855, "casesPerCapita": 276}, "EE": {"totalCases": 1309, "newCases": 5, "active": 1186, "casesPerCapita": 987}, "KW": {"totalCases": 1234, "newCases": 80, "active": 1091, "casesPerCapita": 289}, "SI": {"totalCases": 1205, "newCases": 17, "active": 1002, "casesPerCapita": 580}, "BH": {"totalCases": 1136, "newCases": 96, "active": 572, "casesPerCapita": 668}, "AZ": {"totalCases": 1098, "newCases": 40, "active": 837, "casesPerCapita": 108}, "LT": {"totalCases": 1053, "newCases": 27, "active": 933, "casesPerCapita": 387}, "AM": {"totalCases": 1013, "newCases": 46, "active": 803, "casesPerCapita": 342}, "HK": {"totalCases": 1005, "newCases": 4, "active": 641, "casesPerCapita": 134}, "BA": {"totalCases": 1004, "newCases": 58, "active": 772, "casesPerCapita": 306}, "KZ": {"totalCases": 951, "newCases": 86, "active": 842, "casesPerCapita": 51}, "UZ": {"totalCases": 833, "newCases": 66, "active": 764, "casesPerCapita": 25}, "CM": {"totalCases": 820, "newCases": 0, "active": 710, "casesPerCapita": 31}, "SK": {"totalCases": 742, "newCases": 14, "active": 717, "casesPerCapita": 136}, "TN": {"totalCases": 685, "newCases": 0, "active": 614, "casesPerCapita": 58}, "BG": {"totalCases": 675, "newCases": 14, "active": 578, "casesPerCapita": 97}, "CU": {"totalCases": 669, "newCases": 49, "active": 559, "casesPerCapita": 59}, "LV": {"totalCases": 651, "newCases": 21, "active": 630, "casesPerCapita": 345}, "AD": {"totalCases": 638, "newCases": 37, "active": 481, "casesPerCapita": 8257}, "CY": {"totalCases": 633, "newCases": 17, "active": 557, "casesPerCapita": 524}, "LB": {"totalCases": 630, "newCases": 11, "active": 530, "casesPerCapita": 92}, "BD": {"totalCases": 621, "newCases": 139, "active": 548, "casesPerCapita": 4}, "AF": {"totalCases": 607, "newCases": 52, "active": 557, "casesPerCapita": 16}, "OM": {"totalCases": 599, "newCases": 53, "active": 486, "casesPerCapita": 117}, "CR": {"totalCases": 577, "newCases": 0, "active": 525, "casesPerCapita": 113}, "CI": {"totalCases": 533, "newCases": 0, "active": 471, "casesPerCapita": 20}, "UY": {"totalCases": 501, "newCases": 7, "active": 270, "casesPerCapita": 144}, "NE": {"totalCases": 491, "newCases": 0, "active": 439, "casesPerCapita": 20}, "BF": {"totalCases": 484, "newCases": 0, "active": 302, "casesPerCapita": 23}, "AL": {"totalCases": 446, "newCases": 13, "active": 206, "casesPerCapita": 155}, "GH": {"totalCases": 408, "newCases": 0, "active": 396, "casesPerCapita": 13}, "HN": {"totalCases": 393, "newCases": 1, "active": 361, "casesPerCapita": 40}, "JO": {"totalCases": 389, "newCases": 8, "active": 181, "casesPerCapita": 38}, "TW": {"totalCases": 388, "newCases": 3, "active": 273, "casesPerCapita": 16}, "MT": {"totalCases": 378, "newCases": 8, "active": 331, "casesPerCapita": 856}, "KG": {"totalCases": 377, "newCases": 38, "active": 318, "casesPerCapita": 58}, "SM": {"totalCases": 356, "newCases": 0, "active": 268, "casesPerCapita": 10492}, "MU": {"totalCases": 324, "newCases": 5, "active": 273, "casesPerCapita": 255}, "NG": {"totalCases": 318, "newCases": 0, "active": 238, "casesPerCapita": 2}, "BO": {"totalCases": 300, "newCases": 25, "active": 274, "casesPerCapita": 26}, "PS": {"totalCases": 288, "newCases": 20, "active": 228, "casesPerCapita": 56}, "SN": {"totalCases": 280, "newCases": 2, "active": 107, "casesPerCapita": 17}, "ME": {"totalCases": 267, "newCases": 4, "active": 259, "casesPerCapita": 425}, "VN": {"totalCases": 260, "newCases": 2, "active": 116, "casesPerCapita": 3}, "GE": {"totalCases": 257, "newCases": 15, "active": 187, "casesPerCapita": 64}, "GN": {"totalCases": 250, "newCases": 0, "active": 233, "casesPerCapita": 19}, "IM": {"totalCases": 228, "newCases": 2, "active": 114, "casesPerCapita": 2681}, "DJ": {"totalCases": 214, "newCases": 27, "active": 176, "casesPerCapita": 217}, "LK": {"totalCases": 210, "newCases": 12, "active": 147, "casesPerCapita": 10}, "KE": {"totalCases": 197, "newCases": 6, "active": 164, "casesPerCapita": 4}, "YT": {"totalCases": 196, "newCases": 0, "active": 134, "casesPerCapita": 718}, "VE": {"totalCases": 175, "newCases": 0, "active": 73, "casesPerCapita": 6}, "MQ": {"totalCases": 155, "newCases": 0, "active": 99, "casesPerCapita": 413}, "GT": {"totalCases": 153, "newCases": 16, "active": 131, "casesPerCapita": 9}, "GP": {"totalCases": 143, "newCases": 0, "active": 68, "casesPerCapita": 357}, "PY": {"totalCases": 134, "newCases": 1, "active": 106, "casesPerCapita": 19}, "GI": {"totalCases": 129, "newCases": 0, "active": 45, "casesPerCapita": 3829}, "SV": {"totalCases": 125, "newCases": 7, "active": 98, "casesPerCapita": 19}, "KH": {"totalCases": 122, "newCases": 2, "active": 45, "casesPerCapita": 7}, "RW": {"totalCases": 120, "newCases": 0, "active": 102, "casesPerCapita": 9}, "TT": {"totalCases": 113, "newCases": 1, "active": 93, "casesPerCapita": 81}, "MG": {"totalCases": 106, "newCases": 4, "active": 86, "casesPerCapita": 4}, "ML": {"totalCases": 105, "newCases": 18, "active": 74, "casesPerCapita": 5}, "MC": {"totalCases": 92, "newCases": 0, "active": 86, "casesPerCapita": 2344}, "AW": {"totalCases": 92, "newCases": 0, "active": 63, "casesPerCapita": 862}, "GF": {"totalCases": 86, "newCases": 0, "active": 35, "casesPerCapita": 288}, "LI": {"totalCases": 79, "newCases": 0, "active": 23, "casesPerCapita": 2072}, "TG": {"totalCases": 76, "newCases": 0, "active": 44, "casesPerCapita": 9}, "ET": {"totalCases": 71, "newCases": 2, "active": 58, "casesPerCapita": 0}, "JM": {"totalCases": 69, "newCases": 0, "active": 52, "casesPerCapita": 23}, "BB": {"totalCases": 68, "newCases": 0, "active": 53, "casesPerCapita": 237}, "CG": {"totalCases": 60, "newCases": 0, "active": 50, "casesPerCapita": 11}, "KY": {"totalCases": 53, "newCases": 0, "active": 46, "casesPerCapita": 806}, "UG": {"totalCases": 53, "newCases": 0, "active": 49, "casesPerCapita": 1}, "PF": {"totalCases": 51, "newCases": 0, "active": 51, "casesPerCapita": 182}, "SX": {"totalCases": 50, "newCases": 0, "active": 36, "casesPerCapita": 1166}, "LR": {"totalCases": 50, "newCases": 2, "active": 42, "casesPerCapita": 10}, "BM": {"totalCases": 50, "newCases": 2, "active": 18, "casesPerCapita": 803}, "GA": {"totalCases": 49, "newCases": 3, "active": 47, "casesPerCapita": 22}, "BS": {"totalCases": 46, "newCases": 0, "active": 33, "casesPerCapita": 117}, "GY": {"totalCases": 45, "newCases": 0, "active": 31, "casesPerCapita": 57}, "ZM": {"totalCases": 43, "newCases": 3, "active": 11, "casesPerCapita": 2}, "MM": {"totalCases": 39, "newCases": 1, "active": 33, "casesPerCapita": 0}, "GW": {"totalCases": 38, "newCases": 0, "active": 38, "casesPerCapita": 19}, "BJ": {"totalCases": 35, "newCases": 0, "active": 29, "casesPerCapita": 3}, "ER": {"totalCases": 34, "newCases": 0, "active": 34, "casesPerCapita": 10}, "HT": {"totalCases": 33, "newCases": 0, "active": 30, "casesPerCapita": 3}, "TZ": {"totalCases": 32, "newCases": 0, "active": 24, "casesPerCapita": 0}, "SY": {"totalCases": 25, "newCases": 0, "active": 18, "casesPerCapita": 1}, "LY": {"totalCases": 25, "newCases": 0, "active": 16, "casesPerCapita": 4}, "AG": {"totalCases": 21, "newCases": 0, "active": 19, "casesPerCapita": 214}, "SO": {"totalCases": 21, "newCases": 0, "active": 18, "casesPerCapita": 1}, "GQ": {"totalCases": 21, "newCases": 3, "active": 18, "casesPerCapita": 15}, "MZ": {"totalCases": 21, "newCases": 1, "active": 19, "casesPerCapita": 0}, "MV": {"totalCases": 20, "newCases": 1, "active": 7, "casesPerCapita": 37}, "AO": {"totalCases": 19, "newCases": 0, "active": 13, "casesPerCapita": 0}, "SD": {"totalCases": 19, "newCases": 0, "active": 15, "casesPerCapita": 0}, "LA": {"totalCases": 19, "newCases": 1, "active": 19, "casesPerCapita": 3}, "TD": {"totalCases": 18, "newCases": 7, "active": 16, "casesPerCapita": 1}, "NC": {"totalCases": 18, "newCases": 0, "active": 17, "casesPerCapita": 63}, "DM": {"totalCases": 16, "newCases": 0, "active": 9, "casesPerCapita": 222}, "FJ": {"totalCases": 16, "newCases": 0, "active": 16, "casesPerCapita": 18}, "MN": {"totalCases": 16, "newCases": 0, "active": 12, "casesPerCapita": 5}, "NA": {"totalCases": 16, "newCases": 0, "active": 13, "casesPerCapita": 6}, "LC": {"totalCases": 15, "newCases": 0, "active": 11, "casesPerCapita": 82}, "ZW": {"totalCases": 14, "newCases": 0, "active": 11, "casesPerCapita": 0}, "BZ": {"totalCases": 14, "newCases": 1, "active": 12, "casesPerCapita": 35}, "CW": {"totalCases": 14, "newCases": 0, "active": 6, "casesPerCapita": 85}, "GD": {"totalCases": 14, "newCases": 0, "active": 14, "casesPerCapita": 124}, "SZ": {"totalCases": 14, "newCases": 2, "active": 7, "casesPerCapita": 12}, "MW": {"totalCases": 13, "newCases": 1, "active": 11, "casesPerCapita": 0}, "BW": {"totalCases": 13, "newCases": 0, "active": 12, "casesPerCapita": 6}, "NP": {"totalCases": 12, "newCases": 3, "active": 11, "casesPerCapita": 0}, "KN": {"totalCases": 12, "newCases": 0, "active": 12, "casesPerCapita": 226}, "GL": {"totalCases": 11, "newCases": 0, "active": 0, "casesPerCapita": 194}, "SC": {"totalCases": 11, "newCases": 0, "active": 11, "casesPerCapita": 112}, "SR": {"totalCases": 10, "newCases": 0, "active": 5, "casesPerCapita": 17}, "SL": {"totalCases": 10, "newCases": 0, "active": 10, "casesPerCapita": 1}, "GM": {"totalCases": 9, "newCases": 0, "active": 6, "casesPerCapita": 4}, "NI": {"totalCases": 9, "newCases": 0, "active": 4, "casesPerCapita": 1}, "MS": {"totalCases": 9, "newCases": 0, "active": 9, "casesPerCapita": 1803}, "VA": {"totalCases": 8, "newCases": 0, "active": 6, "casesPerCapita": 9988}, "MR": {"totalCases": 7, "newCases": 0, "active": 4, "casesPerCapita": 2}, "EH": {"totalCases": 6, "newCases": 0, "active": 6, "casesPerCapita": 10}, "BT": {"totalCases": 5, "newCases": 0, "active": 3, "casesPerCapita": 6}, "BI": {"totalCases": 5, "newCases": 0, "active": 5, "casesPerCapita": 0}, "FK": {"totalCases": 5, "newCases": 0, "active": 4, "casesPerCapita": 1437}, "SS": {"totalCases": 4, "newCases": 0, "active": 4, "casesPerCapita": 0}, "AI": {"totalCases": 3, "newCases": 0, "active": 3, "casesPerCapita": 200}, "VG": {"totalCases": 3, "newCases": 0, "active": 1, "casesPerCapita": 99}, "BQ": {"totalCases": 3, "newCases": 1, "active": 3, "casesPerCapita": 114}, "PG": {"totalCases": 2, "newCases": 0, "active": 2, "casesPerCapita": 0}, "TL": {"totalCases": 2, "newCases": 0, "active": 1, "casesPerCapita": 2}, "YE": {"totalCases": 1, "newCases": 0, "active": 1, "casesPerCapita": 0}, "CN": {"totalCases": 82052, "newCases": 99, "active": 1138, "casesPerCapita": 57}}